clone/__init__.py
clone/__main__.py
clone/church.py
clone/graphics.py
apollos_clone-0.1.0.dist-info/METADATA
apollos_clone-0.1.0.dist-info/WHEEL
apollos_clone-0.1.0.dist-info/entry_points.txt
apollos_clone-0.1.0.dist-info/top_level.txt
apollos_clone-0.1.0.dist-info/RECORD
