Metadata-Version: 2.1
Name: apollos-clone
Version: 0.1.0
Summary: Clones an Apollos template app
Author-email: Michael Neeley <michael@neeley.dev>
Project-URL: Homepage, https://github.com/apollosproject/clone
Keywords: apollos,church
Classifier: License :: OSI Approved :: MIT License
Classifier: Programming Language :: Python
Classifier: Programming Language :: Python :: 3
Requires-Python: >=3.9
Requires-Dist: pillow
Requires-Dist: requests
Provides-Extra: dev
Requires-Dist: black ; extra == 'dev'
Requires-Dist: bumpver ; extra == 'dev'
Requires-Dist: isort ; extra == 'dev'
Requires-Dist: pip-tools ; extra == 'dev'
Requires-Dist: pytest ; extra == 'dev'
